{
    "@odata.type": "#StorageServiceCollection.StorageServiceCollection",
    "Name": "Storage Service Collection",
    "Members@odata.count": 5,
    "Members": [
        {
            "@odata.id": "/redfish/v1/StorageServices/1"
        },
        {
            "@odata.id": "/redfish/v1/StorageServices/2"
        },
        {
            "@odata.id": "/redfish/v1/StorageServices/FileService"
        },
        {
            "@odata.id": "/redfish/v1/StorageServices/ISC"
        },
        {
            "@odata.id": "/redfish/v1/StorageServices/Simple1"
        }
    ],
    "@odata.id": "/redfish/v1/StorageServices",
    "@Redfish.Copyright": "Copyright 2015-2025 SNIA. All rights reserved."
}