{
    "@odata.type": "#Thermal.v1_7_1.Thermal",
    "Id": "Thermal",
    "Name": "Thermal",
    "Temperatures": [
        {
            "@odata.id": "/redfish/v1/Chassis/StorageChassis1/Thermal#/Temperatures/0",
            "MemberId": "2",
            "Name": "Chassis Intake Temp",
            "SensorNumber": 44,
            "Status": {
                "State": "Enabled",
                "Health": "OK"
            },
            "ReadingCelsius": 25,
            "UpperThresholdNonCritical": 30,
            "UpperThresholdCritical": 40,
            "UpperThresholdFatal": 50,
            "LowerThresholdNonCritical": 10,
            "LowerThresholdCritical": 5,
            "LowerThresholdFatal": 0,
            "PhysicalContext": "Intake",
            "RelatedItem": [
                {
                    "@odata.id": "/redfish/v1/Chassis/StorageChassis1"
                },
                {
                    "@odata.id": "/redfish/v1/Systems/Simple"
                },
                {
                    "@odata.id": "/redfish/v1/Systems/Complex"
                }
            ]
        }
    ],
    "Fans": [
        {
            "@odata.id": "/redfish/v1/Chassis/StorageChassis1/Thermal#/Fans/0",
            "MemberId": "0",
            "FanName": "BaseBoard System Fan",
            "PhysicalContext": "Backplane",
            "Status": {
                "State": "Enabled",
                "Health": "OK"
            },
            "UpperThresholdNonCritical": 42,
            "UpperThresholdCritical": 4200,
            "UpperThresholdFatal": 42,
            "LowerThresholdNonCritical": 42,
            "LowerThresholdCritical": 5,
            "LowerThresholdFatal": 42,
            "Redundancy": [
                {
                    "@odata.id": "/redfish/v1/Chassis/StorageChassis1/Thermal#/Redundancy/0"
                }
            ],
            "RelatedItem": [
                {
                    "@odata.id": "/redfish/v1/Systems/Simple"
                },
                {
                    "@odata.id": "/redfish/v1/Systems/Complex"
                },
                {
                    "@odata.id": "/redfish/v1/Chassis/StorageChassis1"
                }
            ]
        },
        {
            "@odata.id": "/redfish/v1/Chassis/StorageChassis1/Thermal#/Fans/1",
            "MemberId": "1",
            "FanName": "BaseBoard System Fan Backup",
            "PhysicalContext": "Backplane",
            "Status": {
                "State": "Enabled",
                "Health": "OK"
            },
            "UpperThresholdNonCritical": 42,
            "UpperThresholdCritical": 4200,
            "UpperThresholdFatal": 42,
            "LowerThresholdNonCritical": 42,
            "LowerThresholdCritical": 5,
            "LowerThresholdFatal": 42,
            "Redundancy": [
                {
                    "@odata.id": "/redfish/v1/Chassis/StorageChassis1/Power#/Redundancy/0"
                }
            ],
            "RelatedItem": [
                {
                    "@odata.id": "/redfish/v1/Systems/Simple"
                },
                {
                    "@odata.id": "/redfish/v1/Systems/Complex"
                },
                {
                    "@odata.id": "/redfish/v1/Chassis/StorageChassis1"
                }
            ]
        }
    ],
    "Redundancy": [
        {
            "@odata.id": "/redfish/v1/Chassis/StorageChassis1/Thermal#/Redundancy/0",
            "MemberId": "0",
            "Name": "BaseBoard System Fans",
            "RedundancySet": [
                {
                    "@odata.id": "/redfish/v1/Chassis/StorageChassis1/Thermal#/Fans/0"
                },
                {
                    "@odata.id": "/redfish/v1/Chassis/StorageChassis1/Thermal#/Fans/1"
                }
            ],
            "Mode": "N+m",
            "Status": {
                "State": "Enabled",
                "Health": "OK"
            },
            "MinNumNeeded": 1,
            "MaxNumSupported": 2
        }
    ],
    "@odata.id": "/redfish/v1/Chassis/StorageChassis1/Thermal",
    "@Redfish.Copyright": "Copyright 2015-2024 SNIA. All rights reserved."
}
