{
    "@odata.type": "#StorageService.v1_7_0.StorageService",
    "Id": "2",
    "Name": "My Simple Storage Service",
    "Description": "This simple system does not support service levels when provisioning storage",
    "Identifier": {
        "DurableName": "4289a3dd-ba52-41b8-9d3d-38de196e060b",
        "DurableNameFormat": "UUID"
    },
    "ClassesOfService": {
        "@odata.id": "/redfish/v1/StorageServices/2/ClassesOfService"
    },
    "Status": {
        "State": "Enabled",
        "Health": "OK"
    },
    "Metrics": {
        "@odata.id": "/redfish/v1/StorageServices/2/Metrics"
    },
    "StoragePools": {
        "@odata.id": "/redfish/v1/StorageServices/2/StoragePools"
    },
    "Volumes": {
        "@odata.id": "/redfish/v1/StorageServices/2/Volumes"
    },
    "Links": {
        "HostingSystem": {
            "@odata.id": "/redfish/v1/Systems/Complex"
        },
        "DataProtectionLoSCapabilities": {
            "@odata.id": "/redfish/v1/StorageServices/FileService/DataProtectionLoSCapabilities"
        },
        "DataStorageLoSCapabilities": {
            "@odata.id": "/redfish/v1/StorageServices/FileService/DataStorageLoSCapabilities"
        },
        "IOConnectivityLoSCapabilities": {
            "@odata.id": "/redfish/v1/StorageServices/FileService/IOConnectivityLoSCapabilities"
        },
        "IOPerformanceLoSCapabilities": {
            "@odata.id": "/redfish/v1/StorageServices/FileService/IOPerformanceLoSCapabilities"
        }
    },
    "Oem": {},
    "@odata.id": "/redfish/v1/StorageServices/2",
    "@Redfish.Copyright": "Copyright 2015-2024 SNIA. All rights reserved."
}
