{
    "@odata.type": "#StorageGroup.v1_5_0.StorageGroup",
    "Id": "2",
    "Name": "RG_LOB_SQL",
    "Description": "Replication group for SQL LOB app",
    "VolumesAreExposed": true,
    "AccessState": "Optimized",
    "Status": {
        "State": "Enabled",
        "Health": "OK",
        "HealthRollup": "OK"
    },
    "MappedVolumes": [
        {
            "LogicalUnitNumber": "4",
            "Volume": {
                "@odata.id": "/redfish/v1/StorageServices/2/Volumes/4"
            }
        }
    ],
    "ClientEndpointGroups": [],
    "ServerEndpointGroups": [],
    "@odata.id": "/redfish/v1/StorageServices/2/StorageGroups/2",
    "@Redfish.Copyright": "Copyright 2015-2023 SNIA. All rights reserved."
}